{
  "routes": [
    {
      "page": "contract-wizard",
      "staticTemplate": "pages/contract-wizard.html",
      "suggestedUmiRoute": "/subjects/{id}/contract-wizard",
      "referenceStandalone": "../pages/contract-wizard.html"
    },
    {
      "page": "brokerage",
      "staticTemplate": "pages/brokerage.html",
      "suggestedUmiRoute": "/brokerage",
      "referenceStandalone": "../pages/brokerage.html"
    },
    {
      "page": "trust-management",
      "staticTemplate": "pages/trust-management.html",
      "suggestedUmiRoute": "/trust-management",
      "referenceStandalone": "../pages/trust-management.html"
    },
    {
      "page": "agents",
      "staticTemplate": "pages/agents.html",
      "suggestedUmiRoute": "/agents",
      "referenceStandalone": "../pages/agents.html"
    },
    {
      "page": "middle-office-clients",
      "staticTemplate": "pages/middle-office-clients.html",
      "suggestedUmiRoute": "/middle-office/clients",
      "referenceStandalone": "../pages/middle-office-clients.html"
    },
    {
      "page": "middle-office-reports",
      "staticTemplate": "pages/middle-office-reports.html",
      "suggestedUmiRoute": "/middle-office/reports",
      "referenceStandalone": "../pages/middle-office-reports.html"
    },
    {
      "page": "depository",
      "staticTemplate": "pages/depository.html",
      "suggestedUmiRoute": "/depository",
      "referenceStandalone": "../pages/depository.html"
    },
    {
      "page": "back-office",
      "staticTemplate": "pages/back-office.html",
      "suggestedUmiRoute": "/back-office",
      "referenceStandalone": "../pages/back-office.html"
    },
    {
      "page": "trading-card",
      "staticTemplate": "pages/trading-card.html",
      "suggestedUmiRoute": "/trading/{id}",
      "referenceStandalone": "../pages/trading-card.html"
    },
    {
      "page": "administration",
      "staticTemplate": "pages/administration.html",
      "suggestedUmiRoute": "/administration",
      "referenceStandalone": "../pages/administration.html"
    },
    {
      "page": "archive",
      "staticTemplate": "pages/archive.html",
      "suggestedUmiRoute": "/archive",
      "referenceStandalone": "../pages/archive.html"
    }
  ],
  "entities": [
    "admin-section",
    "agent",
    "archive-record",
    "archive-table",
    "back-office-report",
    "brokerage-contract",
    "contract",
    "contract-delivery",
    "contract-form-section",
    "contract-settings",
    "depository-report",
    "middle-office-client",
    "page-title",
    "report",
    "report-delivery-status",
    "report-detail",
    "report-split-view",
    "trading-profile",
    "trading-terminal",
    "trading-terminal-list",
    "trust-contract"
  ],
  "actions": [
    "add-agent",
    "admin-section-select",
    "create-contract",
    "download-report",
    "export-brokerage",
    "export-contract",
    "export-reports",
    "filter-agents",
    "filter-archive",
    "filter-back-office",
    "filter-brokerage",
    "filter-depository",
    "filter-middle-office-clients",
    "filter-middle-office-reports",
    "filter-trust-management",
    "issue-terminal",
    "open-subject-card",
    "resend-report",
    "reset-filters",
    "reset-terminal-password",
    "restore-archive-record",
    "save-contract",
    "select-report",
    "submit-contract-wizard",
    "switch-tab",
    "view-archive-record"
  ],
  "forms": [
    "agents-filters",
    "archive-filters",
    "back-office-filters",
    "brokerage-filters",
    "contract-wizard",
    "depository-filters",
    "middle-office-clients-filters",
    "middle-office-reports-filters",
    "trust-management-filters"
  ],
  "filters": [
    "agents",
    "archive",
    "back-office",
    "brokerage",
    "depository",
    "middle-office-clients",
    "middle-office-reports",
    "trust-management"
  ],
  "statuses": [
    "active",
    "archived",
    "connected",
    "delivered",
    "delivery-edo",
    "delivery-email",
    "delivery-error",
    "delivery-sftp",
    "paused",
    "pending-approval",
    "qualified-investor",
    "request-waiting",
    "risk-medium"
  ]
}
